Metadata-Version: 1.2
Name: grvlms-figures
Version: 1.0.1
Summary: A Grvlms plugin for Figures, the Open edX reporting and data retrieval app
Home-page: https://groove.education/
Author: Overhang.io
Author-email: thuan.ha@grovoetechnology.com
License: AGPLv3
Project-URL: Documentation, https://groove.education/
Project-URL: Code, https://github.com/groovetch/grvlms-figures
Project-URL: Issue tracker, https://github.com/groovetch/grvlms-figures/issues
Project-URL: Community, https://groove.education/
Platform: UNKNOWN
Classifier: Development Status :: 3 - Alpha
Classifier: Intended Audience :: Developers
Classifier: License :: OSI Approved :: GNU Affero General Public License v3
Classifier: Operating System :: OS Independent
Classifier: Programming Language :: Python
Classifier: Programming Language :: Python :: 3.5
Classifier: Programming Language :: Python :: 3.6
Classifier: Programming Language :: Python :: 3.7
Classifier: Programming Language :: Python :: 3.8
Requires-Python: >=3.5
